Metadata-Version: 2.1
Name: xrcat
Version: 1.0.0
Summary: A small tool for retriving resources from Xresources
Home-page: https://github.com/HolmDev/xrcat
Author: HolmDev
Author-email: fredholm.xyz@protonmail.com
License: GPLv3
Keywords: xrcat,xrdb,xorg,xresources
Classifier: Environment :: X11 Applications
Classifier: License :: OSI Approved :: GNU General Public License v3 (GPLv3)
Classifier: Operating System :: POSIX :: Linux
Classifier: Programming Language :: Python :: 3.6
Requires-Python: >=3.6, <4
License-File: LICENSE
